tmpl8/__init__.py
tmpl8/cli.py
tmpl8/command.py
tmpl8/data.py
tmpl8/template.py
tmpl8-0.1.1.dist-info/LICENSE
tmpl8-0.1.1.dist-info/METADATA
tmpl8-0.1.1.dist-info/WHEEL
tmpl8-0.1.1.dist-info/entry_points.txt
tmpl8-0.1.1.dist-info/top_level.txt
tmpl8-0.1.1.dist-info/RECORD
